{"entityTypes":[{"name":"User","key":"id","properties":[{"name":"id","nullable":false,"type":"Edm.String"},{"name":"username","nullable":false,"type":"Edm.String"},{"name":"googleId","nullable":false,"type":"Edm.Int64"}]},{"name":"Task","key":"id","properties":[{"name":"id","nullable":false,"type":"Edm.String"}]},{"name":"TestEntry","key":"id","properties":[{"name":"id","nullable":false,"type":"Edm.Int16"},{"name":"value","nullable":false,"type":"Edm.String"}]}],"entitySets":[{"name":"users","entityType":"User"},{"name":"tasks","entityType":"Task"},{"name":"testEntries","entityType":"TestEntry"}],"actions":[{"name":"login","function":"LoginAction","isBound":false,"parameters":[{"type":"String","name":"username"},{"type":"String","name":"password"}],"returnType":"User"},{"name":"logout","function":"LogoutAction","isBound":false,"parameters":[],"returnType":"User"},{"name":"mock","function":"MockAction","isBound":true,"parameters":[{"type":"User","name":"bindingParameter"}]}],"functions":[{"name":"getCurrentUser","function":"GetCurrentUser","isBound":false,"parameters":[],"returnType":"User"},{"name":"current","function":"GetCurrentUser","isBound":true,"parameters":[{"type":"Collection(User)","name":"bindingParameter"}],"returnType":"User"},{"name":"mock","function":"MockAction","isBound":true,"parameters":[{"type":"User","name":"bindingParameter"}]}]}